mygameutils/__init__.py
mygameutils/collision.py
mygameutils/movement.py
mygameutils/timer.py
mygameutils/vector.py
pixelcraft-0.1.1.dist-info/METADATA
pixelcraft-0.1.1.dist-info/WHEEL
pixelcraft-0.1.1.dist-info/top_level.txt
pixelcraft-0.1.1.dist-info/RECORD
