Metadata-Version: 2.4
Name: pixelcraft
Version: 0.1.1
Summary: A lightweight Python gaming utility library with vector math, collisions, timers, and movement helpers.
Author: Shrey Kalkhnday
Author-email: developershreyk@gmail.com
Classifier: Programming Language :: Python :: 3
Classifier: Topic :: Games/Entertainment
Classifier: Topic :: Software Development :: Libraries
Classifier: License :: OSI Approved :: MIT License
Classifier: Operating System :: OS Independent
Requires-Python: >=3.7
Dynamic: author
Dynamic: author-email
Dynamic: classifier
Dynamic: description-content-type
Dynamic: requires-python
Dynamic: summary
